README.rst
setup.py
AsyncLupa.egg-info/PKG-INFO
AsyncLupa.egg-info/SOURCES.txt
AsyncLupa.egg-info/dependency_links.txt
AsyncLupa.egg-info/requires.txt
AsyncLupa.egg-info/top_level.txt
asynclupa/__init__.py
asynclupa/_async_lupa.py
asynclupa/version.py