Metadata-Version: 2.1
Name: AsyncLupa
Version: 1.0
Summary: A async wrapper for Lupa
Home-page: https://github.com/SoulSen/AsyncLupa
Author: SoulSen
License: MIT
Project-URL: Documentation, https://github.com/SoulSen/AsyncLupa/blob/master/README.rst
Project-URL: Issue tracker, https://github.com/SoulSen/AsyncLupa/issues
Platform: UNKNOWN
Classifier: Development Status :: 5 - Production/Stable
Classifier: Intended Audience :: Developers
Classifier: Intended Audience :: Information Technology
Classifier: License :: OSI Approved :: MIT License
Classifier: Programming Language :: Python :: 2
Classifier: Programming Language :: Python :: 2.7
Classifier: Programming Language :: Python :: 3
Classifier: Programming Language :: Python :: 3.5
Classifier: Programming Language :: Python :: 3.6
Classifier: Programming Language :: Python :: 3.7
Classifier: Programming Language :: Python :: 3.8
Classifier: Programming Language :: Other Scripting Engines
Classifier: Operating System :: OS Independent
Classifier: Topic :: Software Development
Requires-Python: >=2
